sap_datasphere_mcp/__init__.py
sap_datasphere_mcp/auth.py
sap_datasphere_mcp/cache.py
sap_datasphere_mcp/client.py
sap_datasphere_mcp/config.py
sap_datasphere_mcp/models.py
sap_datasphere_mcp/test_list_assets.py
sap_datasphere_mcp/plugins/__init__.py
sap_datasphere_mcp/plugins/registry.py
sap_datasphere_mcp/tools/__init__.py
sap_datasphere_mcp/tools/catalog.py
sap_datasphere_mcp/tools/connections.py
sap_datasphere_mcp/tools/data.py
sap_datasphere_mcp/tools/spaces.py
sap_datasphere_mcp/tools/tasks.py
sap_datasphere_mcp/transports/http_server.py
sap_datasphere_mcp/transports/stdio_server.py
mcp_sap_datasphere_server-0.3.0.dist-info/METADATA
mcp_sap_datasphere_server-0.3.0.dist-info/WHEEL
mcp_sap_datasphere_server-0.3.0.dist-info/entry_points.txt
mcp_sap_datasphere_server-0.3.0.dist-info/licenses/LICENSE
mcp_sap_datasphere_server-0.3.0.dist-info/RECORD
