Metadata-Version: 2.4
Name: mcp-sap-datasphere-server
Version: 0.3.0
Summary: MCP server exposing SAP Datasphere tools and resources
Author: Rahul Sethi
License: MIT License
License-File: LICENSE
Requires-Python: >=3.10
Requires-Dist: httpx>=0.27.0
Requires-Dist: mcp>=1.2.0
Requires-Dist: pydantic>=2.7.0
Provides-Extra: dev
Requires-Dist: pytest-asyncio>=0.23.0; extra == 'dev'
Requires-Dist: pytest>=8.3.0; extra == 'dev'
Requires-Dist: ruff>=0.5.0; extra == 'dev'
